{"name":"package","className":"ModuleScript","filePaths":["src/init.luau","default.project.json"],"children":[{"name":"CONSTANTS","className":"ModuleScript","filePaths":["src/CONSTANTS.luau"]},{"name":"Debug","className":"ModuleScript","filePaths":["src/Debug.luau"]},{"name":"ENV","className":"ModuleScript","filePaths":["src/ENV.luau"]},{"name":"Parameter","className":"ModuleScript","filePaths":["src/Parameter.luau"]},{"name":"Summary","className":"ModuleScript","filePaths":["src/Summary.luau"]},{"name":"Test","className":"ModuleScript","filePaths":["src/Test.luau"]}]}